paraman/__init__.py
paraman/__main__.py
paraman/cloudformation.py
paraman/config.py
paraman/paraman.py
paraman/parameters.py
paraman-0.0.3.dist-info/METADATA
paraman-0.0.3.dist-info/WHEEL
paraman-0.0.3.dist-info/entry_points.txt
paraman-0.0.3.dist-info/top_level.txt
paraman-0.0.3.dist-info/RECORD
