Metadata-Version: 2.1
Name: paraman
Version: 0.0.3
Summary: Python project template
Home-page: https://github.com/doitintl/paraman
Author: Meir Gabay
Author-email: unfor19@gmail.com
License: MIT
Download-URL: https://github.com/unfor19/paraman/archive/0.0.3.tar.gz
Project-URL: Documentation, https://github.com/doitintl/paraman
Keywords: python,aws,ssm,parameters,manager,automation
Platform: any
Classifier: Development Status :: 5 - Production/Stable
Classifier: Intended Audience :: Developers
Classifier: Topic :: Software Development :: Build Tools
Classifier: License :: OSI Approved :: MIT License
Classifier: Programming Language :: Python :: 3.6
Classifier: Programming Language :: Python :: 3.7
Classifier: Programming Language :: Python :: 3.8
Classifier: Programming Language :: Python :: 3.9
Classifier: Operating System :: POSIX :: Linux
Classifier: Operating System :: Unix
Classifier: Operating System :: MacOS
Classifier: Operating System :: Microsoft :: Windows
Requires-Python: ~=3.6
Requires-Dist: boto3 (>=1.17.28)
Requires-Dist: Click (>=7.1.1)
Requires-Dist: PyYAML (>=5.4.1)
